totalrecon/__init__.py
totalrecon/ai.py
totalrecon/cert.py
totalrecon/extract.py
totalrecon-0.1.0.dist-info/licenses/LICENSE
totalrecon-0.1.0.dist-info/METADATA
totalrecon-0.1.0.dist-info/WHEEL
totalrecon-0.1.0.dist-info/top_level.txt
totalrecon-0.1.0.dist-info/RECORD
