Metadata-Version: 2.4
Name: totalrecon
Version: 0.1.0
Summary: Passive recon extractor and AI summarizer for CTFs, red teams, and open-source recon tooling.
Home-page: https://github.com/josh1643/totalrecon
Author: Joshua Wasserman
Classifier: Programming Language :: Python :: 3
Classifier: License :: OSI Approved :: MIT License
Classifier: Operating System :: OS Independent
Classifier: Intended Audience :: Developers
Classifier: Intended Audience :: Information Technology
Classifier: Topic :: Security
Classifier: Topic :: Utilities
Requires-Python: >=3.8
License-File: LICENSE
Requires-Dist: transformers>=4.25.1
Requires-Dist: torch>=1.10.0
Requires-Dist: requests>=2.28.0
Requires-Dist: PyMuPDF>=1.22.0
Dynamic: author
Dynamic: classifier
Dynamic: description
Dynamic: description-content-type
Dynamic: home-page
Dynamic: license-file
Dynamic: requires-dist
Dynamic: requires-python
Dynamic: summary
